simple_text_processor/__init__.py
simple_text_processor/processor.py
simple_text_processor-0.1.0.dist-info/METADATA
simple_text_processor-0.1.0.dist-info/WHEEL
simple_text_processor-0.1.0.dist-info/top_level.txt
simple_text_processor-0.1.0.dist-info/RECORD
