Metadata-Version: 2.1
Name: simple_text_processor
Version: 0.1.0
Summary: A lightweight utility for common text preparation tasks in ML and NLP.
Home-page: https://github.com/yourusername/simple_text_processor
Author: Your Name
Author-email: your.email@example.com
License: MIT
Classifier: Programming Language :: Python :: 3
Classifier: License :: OSI Approved :: MIT License
Classifier: Operating System :: OS Independent
Classifier: Topic :: Scientific/Engineering :: Artificial Intelligence
Classifier: Topic :: Text Processing
Requires-Python: >=3.6
Requires-Dist: numpy>=1.20.0
